self_certifi/__init__.py
self_certifi/py.typed
self_certifi-2.0.0.dist-info/licenses/LICENSE
self_certifi-2.0.0.dist-info/METADATA
self_certifi-2.0.0.dist-info/WHEEL
self_certifi-2.0.0.dist-info/top_level.txt
self_certifi-2.0.0.dist-info/RECORD
