Metadata-Version: 2.4
Name: self-certifi
Version: 2.0.0
Summary: Create a CA-bundle based on certifi and self-signed certificates, for usage with requests.
Author-email: Maykin Media <support@maykinmedia.nl>
License-Expression: MIT
Project-URL: Homepage, https://github.com/maykinmedia/self-certifi
Project-URL: Bug Tracker, https://github.com/maykinmedia/self-certifi/issues
Project-URL: Source Code, https://github.com/maykinmedia/self-certifi
Keywords: requests,certifi,self-signed,certificates
Classifier: Development Status :: 5 - Production/Stable
Classifier: Intended Audience :: Developers
Classifier: Operating System :: Unix
Classifier: Operating System :: MacOS
Classifier: Operating System :: Microsoft :: Windows
Classifier: Programming Language :: Python :: 3.10
Classifier: Programming Language :: Python :: 3.11
Classifier: Programming Language :: Python :: 3.12
Classifier: Programming Language :: Python :: 3.13
Classifier: Topic :: Software Development :: Libraries :: Python Modules
Requires-Python: >=3.10
License-File: LICENSE
Requires-Dist: certifi
Provides-Extra: tests
Requires-Dist: pytest; extra == "tests"
Requires-Dist: pytest-cov; extra == "tests"
Requires-Dist: tox; extra == "tests"
Requires-Dist: ruff; extra == "tests"
Provides-Extra: release
Requires-Dist: bump-my-version; extra == "release"
Dynamic: license-file
